fastapi_dynamic_router/__init__.py
fastapi_dynamic_router/directory_processor.py
fastapi_dynamic_router/dynamic_router.py
fastapi_dynamic_router/route_registrar.py
fastapi_dynamic_router/utils/param_parser.py
fastapi_dynamic_router-0.1.4.dist-info/METADATA
fastapi_dynamic_router-0.1.4.dist-info/WHEEL
fastapi_dynamic_router-0.1.4.dist-info/licenses/LICENSE
fastapi_dynamic_router-0.1.4.dist-info/RECORD
