Metadata-Version: 2.4
Name: fastapi-dynamic-router
Version: 0.1.4
Summary: A FastAPI extension for dynamic and automatic route registration
Project-URL: Homepage, https://github.com/fastapi-dynamic-router
Project-URL: Bug Tracker, https://github.com/fastapi-dynamic-router/issues
Author-email: Antony Jaen Viquez <tonyjaen0@gmail.com>
License-File: LICENSE
Classifier: Framework :: FastAPI
Classifier: License :: OSI Approved :: MIT License
Classifier: Operating System :: OS Independent
Classifier: Programming Language :: Python :: 3
Requires-Python: >=3.7
Requires-Dist: fastapi>=0.100.0
Requires-Dist: uvicorn>=0.22.0
